{
    "allTileGroupsSettings": [
        {
            "position": {
                "x": 355.3333740234375,
                "y": 1699.3333740234375,
                "z": 0.0
            },
            "rotation": {
                "x": 0.0,
                "y": 0.0,
                "z": 0.0
            },
            "tileCount": 2,
            "allTilesSettings": [
                {
                    "position": {
                        "x": 355.3333740234375,
                        "y": 1699.3333740234375,
                        "z": 0.0
                    },
                    "rotation": {
                        "x": 0.0,
                        "y": 0.0,
                        "z": 0.0
                    },
                    "imageId": 0
                },
                {
                    "position": {
                        "x": 355.3333740234375,
                        "y": 1745.3333740234375,
                        "z": 0.0
                    },
                    "rotation": {
                        "x": 0.0,
                        "y": 0.0,
                        "z": 0.0
                    },
                    "imageId": 1
                }
            ]
        },
        {
            "position": {
                "x": 517.8333740234375,
                "y": 1699.3333740234375,
                "z": 0.0
            },
            "rotation": {
                "x": 0.0,
                "y": 0.0,
                "z": 0.0
            },
            "tileCount": 2,
            "allTilesSettings": [
                {
                    "position": {
                        "x": 517.8333740234375,
                        "y": 1699.3333740234375,
                        "z": 0.0
                    },
                    "rotation": {
                        "x": 0.0,
                        "y": 0.0,
                        "z": 0.0
                    },
                    "imageId": 2
                },
                {
                    "position": {
                        "x": 517.8333740234375,
                        "y": 1745.3333740234375,
                        "z": 0.0
                    },
                    "rotation": {
                        "x": 0.0,
                        "y": 0.0,
                        "z": 0.0
                    },
                    "imageId": 0
                }
            ]
        },
        {
            "position": {
                "x": 680.3333740234375,
                "y": 1699.3333740234375,
                "z": 0.0
            },
            "rotation": {
                "x": 0.0,
                "y": 0.0,
                "z": 0.0
            },
            "tileCount": 2,
            "allTilesSettings": [
                {
                    "position": {
                        "x": 680.3333740234375,
                        "y": 1699.3333740234375,
                        "z": 0.0
                    },
                    "rotation": {
                        "x": 0.0,
                        "y": 0.0,
                        "z": 0.0
                    },
                    "imageId": 2
                },
                {
                    "position": {
                        "x": 680.3333740234375,
                        "y": 1745.3333740234375,
                        "z": 0.0
                    },
                    "rotation": {
                        "x": 0.0,
                        "y": 0.0,
                        "z": 0.0
                    },
                    "imageId": 3
                }
            ]
        },
        {
            "position": {
                "x": 842.8333740234375,
                "y": 1699.3333740234375,
                "z": 0.0
            },
            "rotation": {
                "x": 0.0,
                "y": 0.0,
                "z": 0.0
            },
            "tileCount": 2,
            "allTilesSettings": [
                {
                    "position": {
                        "x": 842.8333740234375,
                        "y": 1699.3333740234375,
                        "z": 0.0
                    },
                    "rotation": {
                        "x": 0.0,
                        "y": 0.0,
                        "z": 0.0
                    },
                    "imageId": 0
                },
                {
                    "position": {
                        "x": 842.8333740234375,
                        "y": 1745.3333740234375,
                        "z": 0.0
                    },
                    "rotation": {
                        "x": 0.0,
                        "y": 0.0,
                        "z": 0.0
                    },
                    "imageId": 0
                }
            ]
        },
        {
            "position": {
                "x": 436.58331298828127,
                "y": 1482.6666259765625,
                "z": 0.0
            },
            "rotation": {
                "x": 0.0,
                "y": 0.0,
                "z": 0.0
            },
            "tileCount": 2,
            "allTilesSettings": [
                {
                    "position": {
                        "x": 436.58331298828127,
                        "y": 1482.6666259765625,
                        "z": 0.0
                    },
                    "rotation": {
                        "x": 0.0,
                        "y": 0.0,
                        "z": 0.0
                    },
                    "imageId": 2
                },
                {
                    "position": {
                        "x": 436.58331298828127,
                        "y": 1528.666748046875,
                        "z": 0.0
                    },
                    "rotation": {
                        "x": 0.0,
                        "y": 0.0,
                        "z": 0.0
                    },
                    "imageId": 0
                }
            ]
        },
        {
            "position": {
                "x": 595.8333129882813,
                "y": 1482.6666259765625,
                "z": 0.0
            },
            "rotation": {
                "x": 0.0,
                "y": 0.0,
                "z": 0.0
            },
            "tileCount": 2,
            "allTilesSettings": [
                {
                    "position": {
                        "x": 595.8333129882813,
                        "y": 1482.6666259765625,
                        "z": 0.0
                    },
                    "rotation": {
                        "x": 0.0,
                        "y": 0.0,
                        "z": 0.0
                    },
                    "imageId": 3
                },
                {
                    "position": {
                        "x": 595.8333129882813,
                        "y": 1528.666748046875,
                        "z": 0.0
                    },
                    "rotation": {
                        "x": 0.0,
                        "y": 0.0,
                        "z": 0.0
                    },
                    "imageId": 1
                }
            ]
        },
        {
            "position": {
                "x": 765.9166870117188,
                "y": 1482.6666259765625,
                "z": 0.0
            },
            "rotation": {
                "x": 0.0,
                "y": 0.0,
                "z": 0.0
            },
            "tileCount": 2,
            "allTilesSettings": [
                {
                    "position": {
                        "x": 765.9166870117188,
                        "y": 1482.6666259765625,
                        "z": 0.0
                    },
                    "rotation": {
                        "x": 0.0,
                        "y": 0.0,
                        "z": 0.0
                    },
                    "imageId": 2
                },
                {
                    "position": {
                        "x": 765.9166870117188,
                        "y": 1528.666748046875,
                        "z": 0.0
                    },
                    "rotation": {
                        "x": 0.0,
                        "y": 0.0,
                        "z": 0.0
                    },
                    "imageId": 1
                }
            ]
        },
        {
            "position": {
                "x": 422.5,
                "y": 1157.6666259765625,
                "z": 0.0
            },
            "rotation": {
                "x": 0.0,
                "y": 0.0,
                "z": 0.0
            },
            "tileCount": 5,
            "allTilesSettings": [
                {
                    "position": {
                        "x": 422.5,
                        "y": 1157.6666259765625,
                        "z": 0.0
                    },
                    "rotation": {
                        "x": 0.0,
                        "y": 0.0,
                        "z": 0.0
                    },
                    "imageId": 3
                },
                {
                    "position": {
                        "x": 407.1666564941406,
                        "y": 1157.6666259765625,
                        "z": 0.0
                    },
                    "rotation": {
                        "x": 0.0,
                        "y": 0.0,
                        "z": 0.0
                    },
                    "imageId": 1
                },
                {
                    "position": {
                        "x": 391.83331298828127,
                        "y": 1157.6666259765625,
                        "z": 0.0
                    },
                    "rotation": {
                        "x": 0.0,
                        "y": 0.0,
                        "z": 0.0
                    },
                    "imageId": 3
                },
                {
                    "position": {
                        "x": 376.5,
                        "y": 1157.6666259765625,
                        "z": 0.0
                    },
                    "rotation": {
                        "x": 0.0,
                        "y": 0.0,
                        "z": 0.0
                    },
                    "imageId": 2
                },
                {
                    "position": {
                        "x": 353.5,
                        "y": 1157.6666259765625,
                        "z": 0.0
                    },
                    "rotation": {
                        "x": 0.0,
                        "y": 0.0,
                        "z": 0.0
                    },
                    "imageId": 2
                }
            ]
        },
        {
            "position": {
                "x": 747.5,
                "y": 1157.6666259765625,
                "z": 0.0
            },
            "rotation": {
                "x": 0.0,
                "y": 0.0,
                "z": 0.0
            },
            "tileCount": 5,
            "allTilesSettings": [
                {
                    "position": {
                        "x": 747.5,
                        "y": 1157.6666259765625,
                        "z": 0.0
                    },
                    "rotation": {
                        "x": 0.0,
                        "y": 0.0,
                        "z": 0.0
                    },
                    "imageId": 0
                },
                {
                    "position": {
                        "x": 762.8333740234375,
                        "y": 1157.6666259765625,
                        "z": 0.0
                    },
                    "rotation": {
                        "x": 0.0,
                        "y": 0.0,
                        "z": 0.0
                    },
                    "imageId": 1
                },
                {
                    "position": {
                        "x": 778.1666870117188,
                        "y": 1157.6666259765625,
                        "z": 0.0
                    },
                    "rotation": {
                        "x": 0.0,
                        "y": 0.0,
                        "z": 0.0
                    },
                    "imageId": 3
                },
                {
                    "position": {
                        "x": 793.5,
                        "y": 1157.6666259765625,
                        "z": 0.0
                    },
                    "rotation": {
                        "x": 0.0,
                        "y": 0.0,
                        "z": 0.0
                    },
                    "imageId": 3
                },
                {
                    "position": {
                        "x": 816.5,
                        "y": 1157.6666259765625,
                        "z": 0.0
                    },
                    "rotation": {
                        "x": 0.0,
                        "y": 0.0,
                        "z": 0.0
                    },
                    "imageId": 1
                }
            ]
        }
    ],
    "allSingleTilesSettings": []
}